taxi_data_core/__init__.py
taxi_data_core/blackandwhitecabs_com_au.py
taxi_data_core/database.py
taxi_data_core/google_sheets.py
taxi_data_core/nextechgps_com.py
taxi_data_core/schema.py
taxi_data_core-0.1.0.dist-info/LICENSE
taxi_data_core-0.1.0.dist-info/METADATA
taxi_data_core-0.1.0.dist-info/WHEEL
taxi_data_core-0.1.0.dist-info/top_level.txt
taxi_data_core-0.1.0.dist-info/RECORD
