Metadata-Version: 2.1
Name: taxi_data_core
Version: 0.1.0
Summary: Core modules for taxi_data funcitonality.
Home-page: https://github.com/WayneBennett666/taxi-data-core
Author: Wayne Bennett
Author-email: wayne.bennett@live.com
Classifier: Programming Language :: Python :: 3
Classifier: License :: OSI Approved :: MIT License
Classifier: Operating System :: OS Independent
Requires-Python: >=3.11
License-File: LICENSE
Requires-Dist: selenium
Requires-Dist: pydantic
Requires-Dist: beautifulsoup4
Requires-Dist: google-auth
Requires-Dist: google-auth-oauthlib
Requires-Dist: google-api-python-client
Requires-Dist: xero-python
Requires-Dist: pandas
